subzone/__init__.py
subzone/__version__.py
subzone/requirements.txt
subzone/subdomain.py
subzone/subzone.py
subzone-0.2.8.dist-info/LICENSE
subzone-0.2.8.dist-info/METADATA
subzone-0.2.8.dist-info/WHEEL
subzone-0.2.8.dist-info/entry_points.txt
subzone-0.2.8.dist-info/top_level.txt
subzone-0.2.8.dist-info/RECORD
