Metadata-Version: 2.1
Name: subzone
Version: 0.2.8
Summary: Subdomains,Dns records, & More!
Home-page: https://github.com/ncorbuk/SubZone
Author: Nathan Corbin
Author-email: ncorbuk@gmail.com
License: UNKNOWN
Platform: UNKNOWN
Classifier: Programming Language :: Python :: 3
Classifier: License :: OSI Approved :: MIT License
Classifier: Operating System :: OS Independent
Requires-Dist: urllib3 (==1.22)
Requires-Dist: requests (==2.18.4)
Requires-Dist: colorama (==0.3.9)
